camect/__init__.py
camect_py-0.1.7.dist-info/LICENSE
camect_py-0.1.7.dist-info/METADATA
camect_py-0.1.7.dist-info/WHEEL
camect_py-0.1.7.dist-info/top_level.txt
camect_py-0.1.7.dist-info/RECORD
