Metadata-Version: 2.1
Name: camect-py
Version: 0.1.7
Summary: A client library to talk to Camect.
Home-page: https://github.com/camect/camect-py
Author: Chao Liu
Author-email: chao@camect.com
License: MIT License
Platform: UNKNOWN
Classifier: Programming Language :: Python :: 3
Classifier: License :: OSI Approved :: MIT License
Classifier: Operating System :: OS Independent
Requires-Python: >=3.6
Requires-Dist: websockets
